{
  "name": "浴血战端-1",
  "author": "和月",
  "start": [
    {
      "map": 1
    },
    {
      "picture\\fanhui_1.png": 1.5
    },
    {
      "picture\\orientation_1.png": 1.5
    },
    {
      "picture\\orientation_6.png": 1.5
    },
    {
      "picture\\map_5-1.png": 1.5
    },
    {
      "picture\\1floor.png": 1.5
    },
    {
      "picture\\map_5-1_point_7.png": 1.5,
      "drag": 1
    },
    {
      "picture\\transfer.png": 1.5
    }
  ],
  "map": [
    {
      "s": 2.5
    },
    {
      "await": 3.0
    },
    {
      "s": 2.4
    },
    {
      "fighting": 2
    },
    {
      "s": 6.0
    },
    {
      "await": 3.0
    },
    {
      "s": 16.0
    },
    {
      "fighting": 2
    },
    {
      "s": 2.0
    },
    {
      "fighting": 2
    },
    {
      "fighting": 2
    },
    {
      "s": 1.0
    },
    {
      "fighting": 2
    },
    {
      "s": 9.0
    },
    {
      "fighting": 2
    },
    {
      "fighting": 2
    },
    {
      "s": 3.5
    },
    {
      "fighting": 2
    },
    {
      "s": 14.0
    },
    {
      "a": 3.0
    },
    {
      "w": 3.0
    },
    {
      "a": 3.5
    },
    {
      "s": 1.7
    },
    {
      "await": 0.5
    },
    {
      "fighting": 2
    },
    {
      "fighting": 2
    },
    {
      "d": 0.9
    },
    {
      "f": 15.0
    },
    {
      "a": 2.0
    },
    {
      "fighting": 2
    },
    {
      "s": 0.9
    },
    {
      "f": 15.0
    },
    {
      "a": 0.9
    },
    {
      "w": 6.8
    },
    {
      "d": 1.0
    },
    {
      "s": 1.5
    },
    {
      "a": 1.5
    },
    {
      "await": 2.0
    },
    {
      "w": 1.0
    },
    {
      "d": 3.5
    },
    {
      "fighting": 1
    },
    {
      "d": 5.7
    },
    {
      "fighting": 1
    },
    {
      "w": 6.0
    },
    {
      "a": 3.0
    },
    {
      "fighting": 1
    },
    {
      "fighting": 2
    }
  ]
}